geospacelab/__init__.py
geospacelab/config/__init__.py
geospacelab/config/__mpl__.py
geospacelab/config/_preferences.py
geospacelab/coords/__init__.py
geospacelab/coords/geo_utilities.py
geospacelab/cs/__init__.py
geospacelab/cs/_aacgm.py
geospacelab/cs/_apex.py
geospacelab/cs/_cs_base.py
geospacelab/cs/_geo.py
geospacelab/cs/geo_utilities.py
geospacelab/datahub/__dataset_base__.py
geospacelab/datahub/__init__.py
geospacelab/datahub/__init_dataset.py
geospacelab/datahub/__init_metadata.py
geospacelab/datahub/__init_variable.py
geospacelab/datahub/__metadata_base__.py
geospacelab/datahub/__variable_base__.py
geospacelab/datahub/_dataset_base.py
geospacelab/datahub/_metadata_base.py
geospacelab/datahub/_variable_base.py
geospacelab/datahub/test.py
geospacelab/datahub/sources/__init__.py
geospacelab/datahub/sources/cdaweb/__init__.py
geospacelab/datahub/sources/cdaweb/downloader.py
geospacelab/datahub/sources/cdaweb/downloader_backup.py
geospacelab/datahub/sources/cdaweb/dmsp/__init__.py
geospacelab/datahub/sources/cdaweb/dmsp/ssusi/__init__.py
geospacelab/datahub/sources/cdaweb/dmsp/ssusi/downloader.py
geospacelab/datahub/sources/cdaweb/dmsp/ssusi/edr_aur/__init__.py
geospacelab/datahub/sources/cdaweb/dmsp/ssusi/edr_aur/downloader.py
geospacelab/datahub/sources/cdaweb/dmsp/ssusi/edr_aur/loader.py
geospacelab/datahub/sources/cdaweb/dmsp/ssusi/edr_aur/variable_config.py
geospacelab/datahub/sources/cdaweb/dmsp/ssusi/sdr_disk/__init__.py
geospacelab/datahub/sources/cdaweb/dmsp/ssusi/sdr_disk/downloader.py
geospacelab/datahub/sources/cdaweb/dmsp/ssusi/sdr_disk/loader.py
geospacelab/datahub/sources/cdaweb/dmsp/ssusi/sdr_disk/variable_config.py
geospacelab/datahub/sources/cdaweb/omni/__init__.py
geospacelab/datahub/sources/cdaweb/omni/downloader.py
geospacelab/datahub/sources/cdaweb/omni/loader.py
geospacelab/datahub/sources/cdaweb/omni/variable_config.py
geospacelab/datahub/sources/esa_eo/__init__.py
geospacelab/datahub/sources/esa_eo/swarm/__init__.py
geospacelab-0.12.1.dist-info/licenses/LICENSE
geospacelab-0.12.1.dist-info/METADATA
geospacelab-0.12.1.dist-info/WHEEL
geospacelab-0.12.1.dist-info/top_level.txt
geospacelab-0.12.1.dist-info/RECORD
