Metadata-Version: 2.4
Name: geospacelab
Version: 0.12.1
Summary: Collect, manage, and visualize geospace data.
Home-page: https://github.com/JouleCai/geospacelab
Author: Lei Cai
Author-email: lei.cai@oulu.fi
License: BSD 3-Clause License
Keywords: Geospace,EISCAT,DMSP,Space weather,Ionosphere,Space,Magnetosphere
Classifier: Development Status :: 4 - Beta
Classifier: Intended Audience :: Science/Research
Classifier: Topic :: Scientific/Engineering :: Physics
Classifier: Topic :: Scientific/Engineering :: Visualization
Classifier: Topic :: Scientific/Engineering :: Astronomy
Classifier: Topic :: Software Development :: Build Tools
Classifier: License :: OSI Approved :: BSD License
Classifier: Programming Language :: Python :: 3.9
Classifier: Programming Language :: Python :: 3.10
Classifier: Programming Language :: Python :: 3.11
Classifier: Programming Language :: Python :: 3.12
Requires-Python: >=3.9,<3.13
License-File: LICENSE
Requires-Dist: cython
Requires-Dist: requests>=2.26.0
Requires-Dist: beautifulsoup4>=4.9.3
Requires-Dist: natsort>=7.1.1
Requires-Dist: numpy<2.4.0
Requires-Dist: scipy>=1.6.0
Requires-Dist: h5py>=3.2.1
Requires-Dist: netcdf4>=1.5.7
Requires-Dist: matplotlib>=3.5
Requires-Dist: madrigalweb>=3.3
Requires-Dist: aacgmv2>=2.6.2
Requires-Dist: cdflib>=1.2.3
Requires-Dist: geopack>=1.0.10
Requires-Dist: palettable
Requires-Dist: tqdm
Requires-Dist: toml
Requires-Dist: sscws
Requires-Dist: pandas>=1.5.3
Requires-Dist: keyring
Dynamic: author
Dynamic: author-email
Dynamic: classifier
Dynamic: description
Dynamic: description-content-type
Dynamic: home-page
Dynamic: keywords
Dynamic: license
Dynamic: license-file
Dynamic: requires-dist
Dynamic: requires-python
Dynamic: summary
